CHANGELOG
LICENSE
MANIFEST.in
README.rst
requirements.txt
setup.py
enteletaor.egg-info/PKG-INFO
enteletaor.egg-info/SOURCES.txt
enteletaor.egg-info/dependency_links.txt
enteletaor.egg-info/entry_points.txt
enteletaor.egg-info/requires.txt
enteletaor.egg-info/top_level.txt
enteletaor_lib/__init__.py
enteletaor_lib/api.py
enteletaor_lib/config.py
enteletaor_lib/data.py
enteletaor_lib/enteletaor.py
enteletaor_lib/libs/__init__.py
enteletaor_lib/libs/contrib/__init__.py
enteletaor_lib/libs/contrib/inetnum.py
enteletaor_lib/libs/core/__init__.py
enteletaor_lib/libs/core/bootloader.py
enteletaor_lib/libs/core/cmd.py
enteletaor_lib/libs/core/config.py
enteletaor_lib/libs/core/logger.py
enteletaor_lib/libs/core/models.py
enteletaor_lib/libs/core/structs.py
enteletaor_lib/libs/hooks/__init__.py
enteletaor_lib/libs/hooks/config/__init__.py
enteletaor_lib/modules/__init__.py
enteletaor_lib/modules/brute/__init__.py
enteletaor_lib/modules/brute/authers.py
enteletaor_lib/modules/brute/cmd_brute_main.py
enteletaor_lib/modules/brute/cmd_list_wordlists.py
enteletaor_lib/modules/brute/cracker.py
enteletaor_lib/modules/brute/cracker3.py
enteletaor_lib/modules/brute/exceptions.py
enteletaor_lib/modules/brute/patch.py
enteletaor_lib/modules/brute/utils.py
enteletaor_lib/modules/redis/__init__.py
enteletaor_lib/modules/redis/cmd_actions.py
enteletaor_lib/modules/redis/redis_cache.py
enteletaor_lib/modules/redis/redis_clients.py
enteletaor_lib/modules/redis/redis_disconnect.py
enteletaor_lib/modules/redis/redis_discover_db.py
enteletaor_lib/modules/redis/redis_dump.py
enteletaor_lib/modules/redis/redis_info.py
enteletaor_lib/modules/redis/redis_shell.py
enteletaor_lib/modules/scan/__init__.py
enteletaor_lib/modules/scan/patch.py
enteletaor_lib/modules/scan/scan_main.py
enteletaor_lib/modules/tasks/__init__.py
enteletaor_lib/modules/tasks/cmd_actions.py
enteletaor_lib/modules/tasks/tasks_inject_process.py
enteletaor_lib/modules/tasks/tasks_list_process.py
enteletaor_lib/modules/tasks/tasks_raw_dump.py
enteletaor_lib/modules/tasks/tasks_remove.py
enteletaor_lib/modules/tasks/utils.py
enteletaor_lib/resources/wordlist/10_million_password_list_top_100.txt
