Metadata-Version: 1.1
Name: enteletaor
Version: 1.1.1
Summary: Message Queue & Broker Injection tool
Home-page: https://github.com/cr0hn/enteletaor
Author: Daniel Garcia (cr0hn) - @ggdaniel
Author-email: cr0hn@cr0hn.com
License: BSD
Platform: UNKNOWN
Classifier: Environment :: Console
Classifier: Intended Audience :: System Administrators
Classifier: Intended Audience :: Other Audience
Classifier: License :: OSI Approved :: BSD License
Classifier: Operating System :: MacOS
Classifier: Operating System :: Microsoft :: Windows
Classifier: Operating System :: POSIX
Classifier: Programming Language :: Python :: 2
Classifier: Programming Language :: Python :: 3
Classifier: Topic :: Security
